dlph/__init__.py
dlph/dlph.py
dlph-0.1.3.dist-info/METADATA
dlph-0.1.3.dist-info/WHEEL
dlph-0.1.3.dist-info/top_level.txt
dlph-0.1.3.dist-info/RECORD
