Metadata-Version: 2.1
Name: dlph
Version: 0.1.3
Summary: Deep Learning Print Helper
Home-page: 
Author: Lihao Wang
Author-email: lihaowang@yahoo.com
License: UNKNOWN
Platform: UNKNOWN
Classifier: Programming Language :: Python :: 3
Classifier: License :: OSI Approved :: MIT License
Classifier: Operating System :: OS Independent
Requires-Python: >=3.7
Requires-Dist: numpy
